COPYING
MANIFEST.in
NEWS
README.md
dev-requirements.txt
requirements.txt
setup.py
sopel_modules/__init__.py
sopel_modules.idlerpg.egg-info/PKG-INFO
sopel_modules.idlerpg.egg-info/SOURCES.txt
sopel_modules.idlerpg.egg-info/dependency_links.txt
sopel_modules.idlerpg.egg-info/namespace_packages.txt
sopel_modules.idlerpg.egg-info/top_level.txt
sopel_modules/idlerpg/__init__.py
sopel_modules/idlerpg/idlerpg.py
tests/__init__.py
tests/test_idlerpg.py