Metadata-Version: 1.1
Name: sopel-modules.idlerpg
Version: 0.1.0
Summary: Rewrite of the idlerpg bot in python, using Sopel
Home-page: http://github.com/maxpowa/sopel-idlerpg
Author: Max Gurela
Author-email: maxpowa@outlook.com
License: Eiffel Forum License, version 2
Platform: UNKNOWN
Requires: sopel (>=6.0,<7.0)
